{
	"info": {
		"_postman_id": "54a3cd89-8bda-4a23-8d9c-be3d310cb799",
		"name": "Hotmart-Challenge",
		"schema": "https://schema.getpostman.com/json/collection/v2.1.0/collection.json"
	},
	"item": [
		{
			"name": "Products",
			"item": [
				{
					"name": "List Products",
					"request": {
						"method": "GET",
						"header": [],
						"url": {
							"raw": "localhost:8080/products?page=0&size=30&orderBy=category",
							"host": [
								"localhost"
							],
							"port": "8080",
							"path": [
								"products"
							],
							"query": [
								{
									"key": "page",
									"value": "0"
								},
								{
									"key": "size",
									"value": "30"
								},
								{
									"key": "orderBy",
									"value": "category"
								}
							]
						}
					},
					"response": []
				},
				{
					"name": "Find Product By Id",
					"request": {
						"method": "GET",
						"header": [],
						"url": {
							"raw": "localhost:8080/products/40",
							"host": [
								"localhost"
							],
							"port": "8080",
							"path": [
								"products",
								"40"
							]
						}
					},
					"response": []
				},
				{
					"name": "Delete Product",
					"request": {
						"method": "DELETE",
						"header": [],
						"url": {
							"raw": "localhost:8080/products/3",
							"host": [
								"localhost"
							],
							"port": "8080",
							"path": [
								"products",
								"3"
							]
						}
					},
					"response": []
				},
				{
					"name": "Create Product",
					"request": {
						"method": "POST",
						"header": [],
						"body": {
							"mode": "raw",
							"raw": "{\r\n    \"name\": \"mouse 03\",\r\n    \"description\": \"mouse 03\",\r\n    \"categories\": [\r\n        \"Mouse\"\r\n    ]\r\n}\r\n",
							"options": {
								"raw": {
									"language": "json"
								}
							}
						},
						"url": {
							"raw": "localhost:8080/products",
							"host": [
								"localhost"
							],
							"port": "8080",
							"path": [
								"products"
							]
						}
					},
					"response": []
				},
				{
					"name": "Update Product",
					"request": {
						"method": "PUT",
						"header": [],
						"body": {
							"mode": "raw",
							"raw": "{\r\n    \"id\": 40,\r\n    \"name\": \"Fiat 147\",\r\n    \"description\": \"Fiat 147 novo ( lol )\",\r\n    \"categories\": [\r\n        \"SmartWatch\",\r\n        \"Watch\",\r\n        \"technology\"\r\n    ]\r\n}",
							"options": {
								"raw": {
									"language": "json"
								}
							}
						},
						"url": {
							"raw": "localhost:8080/products",
							"host": [
								"localhost"
							],
							"port": "8080",
							"path": [
								"products"
							]
						}
					},
					"response": []
				}
			],
			"protocolProfileBehavior": {}
		},
		{
			"name": "Customer",
			"item": [
				{
					"name": "Create Customer",
					"request": {
						"method": "POST",
						"header": [],
						"body": {
							"mode": "raw",
							"raw": "{\r\n  \"name\": \"Cliente 17\"\r\n}",
							"options": {
								"raw": {
									"language": "json"
								}
							}
						},
						"url": {
							"raw": "localhost:8080/customers",
							"host": [
								"localhost"
							],
							"port": "8080",
							"path": [
								"customers"
							]
						}
					},
					"response": []
				}
			],
			"protocolProfileBehavior": {}
		},
		{
			"name": "Salesman",
			"item": [
				{
					"name": "Create Salesman",
					"request": {
						"method": "POST",
						"header": [],
						"body": {
							"mode": "raw",
							"raw": "{\r\n\t\"name\": \"Loja 109\"\r\n}",
							"options": {
								"raw": {
									"language": "json"
								}
							}
						},
						"url": {
							"raw": "localhost:8080/salesmans",
							"host": [
								"localhost"
							],
							"port": "8080",
							"path": [
								"salesmans"
							]
						}
					},
					"response": []
				}
			],
			"protocolProfileBehavior": {}
		},
		{
			"name": "Shopping",
			"item": [
				{
					"name": "Buy Product",
					"request": {
						"method": "POST",
						"header": [],
						"body": {
							"mode": "raw",
							"raw": "{\r\n  \"id_customer\": 1,\r\n  \"id_product\": 11,\r\n  \"id_salesman\": 5,\r\n  \"rating\": 2\r\n}",
							"options": {
								"raw": {
									"language": "json"
								}
							}
						},
						"url": {
							"raw": "localhost:8080/shoppings",
							"host": [
								"localhost"
							],
							"port": "8080",
							"path": [
								"shoppings"
							]
						}
					},
					"response": []
				}
			],
			"protocolProfileBehavior": {}
		}
	],
	"protocolProfileBehavior": {}
}